fiction_dl/Configuration.py
fiction_dl/__init__.py
fiction_dl/__main__.py
fiction_dl/Concepts/Chapter.py
fiction_dl/Concepts/Extractor.py
fiction_dl/Concepts/Formatter.py
fiction_dl/Concepts/Image.py
fiction_dl/Concepts/Metadata.py
fiction_dl/Concepts/Processor.py
fiction_dl/Concepts/Story.py
fiction_dl/Concepts/StoryPackage.py
fiction_dl/Concepts/__init__.py
fiction_dl/Core/Application.py
fiction_dl/Core/Cache.py
fiction_dl/Core/InputData.py
fiction_dl/Core/__init__.py
fiction_dl/Extractors/ExtractorAH.py
fiction_dl/Extractors/ExtractorAO3.py
fiction_dl/Extractors/ExtractorAdultFanfiction.py
fiction_dl/Extractors/ExtractorAsstrKristen.py
fiction_dl/Extractors/ExtractorFFNet.py
fiction_dl/Extractors/ExtractorFicWad.py
fiction_dl/Extractors/ExtractorHPFF.py
fiction_dl/Extractors/ExtractorHentaiFoundry.py
fiction_dl/Extractors/ExtractorLiterotica.py
fiction_dl/Extractors/ExtractorNajlepszaErotyka.py
fiction_dl/Extractors/ExtractorNifty.py
fiction_dl/Extractors/ExtractorQuestionableQuesting.py
fiction_dl/Extractors/ExtractorQuotev.py
fiction_dl/Extractors/ExtractorRalst.py
fiction_dl/Extractors/ExtractorReddit.py
fiction_dl/Extractors/ExtractorSamAndJack.py
fiction_dl/Extractors/ExtractorSpaceBattles.py
fiction_dl/Extractors/ExtractorSufficientVelocity.py
fiction_dl/Extractors/ExtractorTextFile.py
fiction_dl/Extractors/ExtractorWhoFic.py
fiction_dl/Extractors/ExtractorWuxiaWorld.py
fiction_dl/Extractors/ExtractorXenForo.py
fiction_dl/Extractors/__init__.py
fiction_dl/Formatters/FormatterEPUB.py
fiction_dl/Formatters/FormatterHTML.py
fiction_dl/Formatters/FormatterMOBI.py
fiction_dl/Formatters/FormatterODT.py
fiction_dl/Formatters/FormatterPDF.py
fiction_dl/Formatters/__init__.py
fiction_dl/Processors/SanitizerProcessor.py
fiction_dl/Processors/TypographyProcessor.py
fiction_dl/Processors/__init__.py
fiction_dl/Resources/PrettyHTMLText.html
fiction_dl/Resources/__init__.py
fiction_dl/Templates/FormatterHTML (Package).html
fiction_dl/Templates/FormatterHTML.html
fiction_dl-1.8.3.dist-info/LICENSE
fiction_dl-1.8.3.dist-info/METADATA
fiction_dl-1.8.3.dist-info/WHEEL
fiction_dl-1.8.3.dist-info/entry_points.txt
fiction_dl-1.8.3.dist-info/top_level.txt
fiction_dl-1.8.3.dist-info/RECORD
