Metadata-Version: 2.1
Name: fiction-dl
Version: 1.8.3
Summary: A content downloader, capable of retrieving works of (fan)fiction from the web and saving them in a few common file formats.
Home-page: http://github.com/DreamCobbler/fiction-dl
Author: Benedykt Synakiewicz
Author-email: dreamcobbler@outlook.com
License: UNKNOWN
Platform: UNKNOWN
Classifier: Development Status :: 5 - Production/Stable
Classifier: Programming Language :: Python :: 3
Classifier: License :: OSI Approved :: GNU General Public License (GPL)
Classifier: Operating System :: OS Independent
Classifier: Environment :: Console
Classifier: Intended Audience :: End Users/Desktop
Classifier: Topic :: Internet :: WWW/HTTP
Requires-Python: >=3.8
Requires-Dist: PyMuPDF
Requires-Dist: bleach
Requires-Dist: bs4
Requires-Dist: dreamy-utilities (>=1.2.0)
Requires-Dist: ebooklib
Requires-Dist: fake-useragent
Requires-Dist: html5lib
Requires-Dist: lxml
Requires-Dist: markdown
Requires-Dist: numpy
Requires-Dist: opencv-python
Requires-Dist: pillow
Requires-Dist: praw
Requires-Dist: pykakasi
Requires-Dist: pyopenssl
